market_data_assembler/__init__.py
market_data_assembler/main.py
market_data_assembler/aggregator/__init__.py
market_data_assembler/aggregator/ohlc_aggregator.py
market_data_assembler/assembling/__init__.py
market_data_assembler/assembling/aggregation_config.py
market_data_assembler/assembling/dataset_assembler.py
market_data_assembler/assembling/dataset_cache.py
market_data_assembler/assembling/historical_assembler_manager.py
market_data_assembler/common/__init__.py
market_data_assembler/common/common.py
market_data_assembler/indicators/__init__.py
market_data_assembler/indicators/indicator_abstract.py
market_data_assembler/indicators/indicator_interface.py
market_data_assembler/indicators/ma_indicator.py
market_data_assembler/labeling/__init__.py
market_data_assembler/labeling/dataset_labeler_abstract.py
market_data_assembler/labeling/volatility_dataset_labeler.py
market_data_assembler/loader/__init__.py
market_data_assembler/loader/book_dept_loader_interface.py
market_data_assembler/loader/ohlc_loader_interface.py
market_data_assembler/loader/trades_loader_interface.py
market_data_assembler/loader/binance_vision/__init__.py
market_data_assembler/loader/binance_vision/book_depth_loader.py
market_data_assembler/loader/binance_vision/ohlc_loader.py
market_data_assembler/loader/binance_vision/trades_loader.py
market_data_assembler/loader/polygon/__init__.py
market_data_assembler/loader/polygon/ohlc_loader.py
market_data_assembler/loader/polygon/trades_loader.py
market_data_assembler/providers/__init__.py
market_data_assembler/providers/crypto_series_data_provider.py
market_data_assembler/providers/stock_series_data_provider.py
market_data_assembler/tests/__init__.py
market_data_assembler/tests/dataset_checking.py
market_data_assembler/tests/aggregator/__init__.py
market_data_assembler/tests/aggregator/test_ohlc_aggregator.py
market_data_assembler/tests/aggregator/test_ohlc_aggregator_expected.py
market_data_assembler-1.2.2.dist-info/METADATA
market_data_assembler-1.2.2.dist-info/WHEEL
market_data_assembler-1.2.2.dist-info/top_level.txt
market_data_assembler-1.2.2.dist-info/RECORD
